LICENSE
README.md
midas.json
setup.cfg
setup.py
midas/__init__.py
midas/config.py
midas/constants.py
midas/context_types.py
midas/midas.py
midas/midas_magic.py
midas/showme.py
midas/state_types.py
midas/ui_comm.py
midas/vis_types.py
midas/midas_algebra/__init__.py
midas/midas_algebra/context.py
midas/midas_algebra/data_types.py
midas/midas_algebra/dataframe.py
midas/midas_algebra/selection.py
midas/static/__init__.py
midas/static/config.py
midas/static/constants.py
midas/static/context_types.py
midas/static/index.js
midas/static/index.js.map
midas/static/midas.py
midas/static/midas_magic.py
midas/static/showme.py
midas/static/state_types.py
midas/static/ui_comm.py
midas/static/vis_types.py
midas/static/midas_algebra/__init__.py
midas/static/midas_algebra/context.py
midas/static/midas_algebra/data_types.py
midas/static/midas_algebra/dataframe.py
midas/static/midas_algebra/selection.py
midas/static/static/__init__.py
midas/static/static/config.py
midas/static/static/constants.py
midas/static/static/context_types.py
midas/static/static/midas.py
midas/static/static/midas_magic.py
midas/static/static/showme.py
midas/static/static/state_types.py
midas/static/static/ui_comm.py
midas/static/static/vis_types.py
midas/static/static/tests/__init__.py
midas/static/static/tests/all.py
midas/static/static/tests/test_rendering.py
midas/static/static/tests/test_util.py
midas/static/static/util/__init__.py
midas/static/static/util/data_processing.py
midas/static/static/util/errors.py
midas/static/static/util/instructions.py
midas/static/static/util/utils.py
midas/static/tests/__init__.py
midas/static/tests/all.py
midas/static/tests/test_rendering.py
midas/static/tests/test_util.py
midas/static/util/__init__.py
midas/static/util/data_processing.py
midas/static/util/errors.py
midas/static/util/instructions.py
midas/static/util/utils.py
midas/tests/__init__.py
midas/tests/all.py
midas/tests/test_rendering.py
midas/tests/test_util.py
midas/util/__init__.py
midas/util/data_processing.py
midas_ext.egg-info/PKG-INFO
midas_ext.egg-info/SOURCES.txt
midas_ext.egg-info/dependency_links.txt
midas_ext.egg-info/top_level.txt