Metadata-Version: 1.1
Name: midas-ext
Version: 0.0.3
Summary: Midas: Reification of interactions in Jupyter Notebook
Home-page: http://github.com/yifanwu/midas
Author: Yifan Wu
Author-email: yifanwu@berkeley.edu
License: BSD 3-clause
Download-URL: http://github.com/yifanwu/midas
Platform: UNKNOWN
Classifier: Development Status :: 2 - Pre-Alpha
Classifier: Environment :: Other Environment
Classifier: Intended Audience :: Science/Research
Classifier: License :: OSI Approved :: Apache Software License
Classifier: Natural Language :: English
Classifier: Programming Language :: Python
Classifier: Programming Language :: Python :: 3.7
